ancv/__init__.py
ancv/__main__.py
ancv/exceptions.py
ancv/py.typed
ancv/reflection.py
ancv/timing.py
ancv/typehelp.py
ancv/data/__init__.py
ancv/data/validation.py
ancv/data/models/__init__.py
ancv/data/models/github.py
ancv/data/models/resume.py
ancv/visualization/__init__.py
ancv/visualization/templates.py
ancv/visualization/themes.py
ancv/visualization/translations.py
ancv/web/__init__.py
ancv/web/client.py
ancv/web/server.py
ancv-1.5.3.dist-info/LICENSE
ancv-1.5.3.dist-info/METADATA
ancv-1.5.3.dist-info/WHEEL
ancv-1.5.3.dist-info/entry_points.txt
ancv-1.5.3.dist-info/top_level.txt
ancv-1.5.3.dist-info/RECORD
