Metadata-Version: 2.1
Name: ancv
Version: 1.5.3
Summary: Renders your (JSON) resume/CV for online & pretty terminal display
Author-email: Alex Povel <python@alexpovel.de>
License: MIT License
Project-URL: Homepage, https://ancv.povel.dev
Project-URL: Repository, https://github.com/alexpovel/ancv/
Project-URL: Issues, https://github.com/alexpovel/ancv/issues/
Project-URL: Changelog, https://github.com/alexpovel/ancv/blob/main/CHANGELOG.md
Classifier: Development Status :: 5 - Production/Stable
Classifier: Environment :: Console
Classifier: Environment :: Web Environment
Classifier: Framework :: AnyIO
Classifier: Framework :: AsyncIO
Classifier: Framework :: Pytest
Classifier: Intended Audience :: Developers
Classifier: Intended Audience :: Information Technology
Classifier: Natural Language :: English
Classifier: Natural Language :: German
Classifier: Operating System :: OS Independent
Classifier: Programming Language :: Python :: 3.12
Classifier: Programming Language :: Python :: Implementation :: CPython
Classifier: Topic :: Internet :: WWW/HTTP
Classifier: Topic :: Office/Business
Classifier: Topic :: System :: Shells
Classifier: Topic :: Terminals
Classifier: Topic :: Terminals :: Terminal Emulators/X Terminals
Classifier: Topic :: Text Processing
Classifier: Topic :: Text Processing :: Markup
Classifier: Typing :: Typed
Requires-Python: >=3.12
License-File: LICENSE
Requires-Dist: gidgethub>=5.3.0
Requires-Dist: aiohttp>=3.10.10
Requires-Dist: structlog>=24.4.0
Requires-Dist: cachetools>=5.5.0
Requires-Dist: humanize>=4.11.0
Requires-Dist: rich>=13.9.3
Requires-Dist: typer>=0.12.5
Requires-Dist: babel>=2.16.0
Requires-Dist: pydantic[email]>=2.9.2
